[
    {
        "year": "2020",
        "date": "THU 17/12",
        "viola": "VIOLA",
        "conductor": "",
        "location": "Liszt Academy of Music, Hungary",
        "programme": [
            "Beethoven Clarinet Trio in B flat major, Op. 11",
            "Balogh TRIOverture for viola, cello, and piano",
            "Brahms Trio Op.114 arr. viola, cello, piano"
        ],
        "pastconcert": true,
        "canceled": false,
        "link": "",
        "withwhom": ""
    },
    {
        "year": "2020",
        "date": "THU 03/12",
        "viola": "VIOLA",
        "conductor": "",
        "location": "Tchaikovsky Concert Hall, Moscow",
        "programme": ["Bruch Concerto for Violin and Viola in E minor, Op. 88"],
        "pastconcert": true,
        "canceled": false,
        "link": "",
        "withwhom": ""
    },
    {
        "year": "2020",
        "date": "THU 29/11",
        "viola": "",
        "conductor": "CONDUCTOR",
        "location": "La Verdi Milan, Italy",
        "programme": ["Shostakovich Symphony No.14"],
        "pastconcert": true,
        "canceled": false,
        "link": "",
        "withwhom": ""
    },
    {
        "year": "2020",
        "date": "FRI 27/11",
        "viola": "",
        "conductor": "CONDUCTOR",
        "location": "La Verdi Milan, Italy",
        "programme": ["Shostakovich Symphony No.14"],
        "pastconcert": true,
        "canceled": false,
        "link": "",
        "withwhom": ""
    },
    {
        "year": "2020",
        "date": "SUN 26/11",
        "viola": "",
        "conductor": "CONDUCTOR",
        "location": "La Verdi Milan, Italy",
        "programme": ["Shostakovich Symphony No.14"],
        "pastconcert": true,
        "canceled": false,
        "link": "",
        "withwhom": ""
    },
    {
        "year": "2020",
        "date": "SUN 23/11",
        "viola": "VIOLA",
        "conductor": "",
        "location": "Gran Canaria, Las Palmas, Spain",
        "programme": [
            "Ichmuratov Homage to Beethoven for trio",
            "Beethoven Clarinet Trio in B flat major, Op. 11",
            "Balogh TRIOverture for viola, cello, and piano",
            "Brahms Trio Op.114 arr. viola, cello, piano"
        ],
        "pastconcert": true,
        "canceled": false,
        "link": "",
        "withwhom": ""
    },
    {
        "year": "2020",
        "date": "WED 28/10",
        "viola": "VIOLA",
        "conductor": "",
        "location": "Sala Verdi Milan, Italy",
        "programme": [],
        "pastconcert": true,
        "canceled": false,
        "link": "",
        "withwhom": ""
    },
    {
        "year": "2020",
        "date": "SUN 20/09",
        "viola": "VIOLA",
        "conductor": "",
        "location": "Laeiszhalle Hamburg, Germany",
        "programme": [
            "Mozart Sinfonia Concertante for Violin, Viola, and Orchestra"
        ],
        "pastconcert": true,
        "canceled": false,
        "link": "",
        "withwhom": ""
    },
    {
        "year": "2020",
        "date": "SUN 19/07",
        "viola": "VIOLA",
        "conductor": "",
        "location": "Musica Mundi Course & Festival",
        "programme": [],
        "pastconcert": true,
        "canceled": false,
        "link": "",
        "withwhom": ""
    },
    {
        "year": "2020",
        "date": "SUN 09/07",
        "viola": "VIOLA",
        "conductor": "",
        "location": "ClasClas Festival",
        "programme": [],
        "pastconcert": true,
        "canceled": false,
        "link": "",
        "withwhom": ""
    },
    {
        "year": "2020",
        "date": "FRI 19/06",
        "viola": "VIOLA",
        "conductor": "",
        "location": "Blaricum Festival, Netherlands",
        "programme": [
            "Beethoven String Quintet, Op. 29",
            "Brahms quintet op. 115 (viola version)"
        ],
        "pastconcert": true,
        "canceled": false,
        "link": "",
        "withwhom": ""
    },
    {
        "year": "2020",
        "date": "MON 15/06",
        "viola": "VIOLA",
        "conductor": "",
        "location": "Philharmonie/Kammermusiksaal, Berlin",
        "programme": [
            "J. Brahms Streichsextett Nr. 1 B-Dur op. 18",
            "J. Brahms Streichsextett Nr. 2 G-Dur op. 36"
        ],
        "pastconcert": true,
        "canceled": false,
        "link": "",
        "withwhom": ""
    },
    {
        "year": "2020",
        "date": "THU 05/05",
        "viola": "VIOLA",
        "conductor": "",
        "location": "Gran Canaria Philharmonic Society",
        "programme": [
            "Beethoven Duet mit zwei obligaten Augengläsern in G major",
            "Chopin Piano Trio, Op.8",
            "Máté Balogh: TRIOverture",
            "Brahms Trio in A minor, Op. 114"
        ],
        "pastconcert": true,
        "canceled": false,
        "link": "",
        "withwhom": ""
    },
    {
        "year": "2020",
        "date": "MON 27/04",
        "viola": "VIOLA",
        "conductor": "",
        "location": "“Music without Limits”, Ukraine, Dnipro",
        "programme": [
            "Giya Kancheli Mourned by the wind",
            "Max Bruch Concerto for Clarinet & Viola, Op. 88"
        ],
        "pastconcert": true,
        "canceled": false,
        "link": "",
        "withwhom": ""
    },
    {
        "year": "2020",
        "date": "SUN 29/03",
        "viola": "",
        "conductor": "CONDUCTOR",
        "location": "National Philharmonic of Ukraine, Kiev",
        "programme": [
            "Mozart Symphony No. 31 in D major 'Paris', K.297/300a",
            "Ibert Concerto for Flute & Orchestra",
            "Poulenc Sinfonietta, FP 141",
            "Malcom Arnold Variations on a Ukrainian folk song for string orchestra (arr. Roger Steptoe)"
        ],
        "pastconcert": true,
        "canceled": false,
        "link": "",
        "withwhom": ""
    },
    {
        "year": "2020",
        "date": "SUN 01/03",
        "viola": "",
        "conductor": "CONDUCTOR",
        "location": "Auditorium di Milano",
        "programme": [
            "Tchaikovsky Serenade for Strings in C major, Op. 48",
            "Zago Tropfen II",
            "Tchaikovsky Symphony No. 6 in B minor, Op. 74"
        ],
        "pastconcert": true,
        "canceled": false,
        "link": "",
        "withwhom": ""
    },
    {
        "year": "2020",
        "date": "SAT 28/02",
        "viola": "",
        "conductor": "CONDUCTOR",
        "location": "Auditorium di Milano",
        "programme": [
            "Tchaikovsky Serenade for Strings in C major, Op. 48",
            "Zago Tropfen II",
            "Tchaikovsky Symphony No. 6 in B minor, Op. 74"
        ],
        "pastconcert": true,
        "canceled": false,
        "link": "",
        "withwhom": ""
    },
    {
        "year": "2020",
        "date": "FRI 27/02",
        "viola": "",
        "conductor": "CONDUCTOR",
        "location": "Auditorium di Milano",
        "programme": [
            "Tchaikovsky Serenade for Strings in C major, Op. 48",
            "Zago Tropfen II",
            "Tchaikovsky Symphony No. 6 in B minor, Op. 74"
        ],
        "pastconcert": true,
        "canceled": false,
        "link": "",
        "withwhom": ""
    },
    {
        "year": "2020",
        "date": "FRI 21/02",
        "viola": "VIOLA",
        "conductor": "",
        "location": "Avenida Príncipe de Asturias, Las Palmas de Gran Canaria",
        "programme": ["Tchaikovsky Variations on a Rococo Theme, Op. 33"],
        "pastconcert": true,
        "canceled": false,
        "link": "",
        "withwhom": ""
    },
    {
        "year": "2020",
        "date": "SUN 17/01",
        "viola": "VIOLA",
        "conductor": "",
        "location": "BBC Radio 3 Lunchtime Concert, LSO St Luke's, London",
        "programme": [
            "Bach Cello Suite No 1 (arr for viola)",
            "Two-Part Inventions for violin and viola",
            "Sonata for viola da gamba in G major"
        ],
        "pastconcert": true,
        "canceled": false,
        "link": "",
        "withwhom": ""
    }
]